LICENSE.txt
setup.py
pyqpath/__init__.py
pyqpath/_version.py
pyqpath/discrete_Morse.py
pyqpath/path_weights.py
pyqpath/plot_digraph.py
pyqpath.egg-info/PKG-INFO
pyqpath.egg-info/SOURCES.txt
pyqpath.egg-info/dependency_links.txt
pyqpath.egg-info/not-zip-safe
pyqpath.egg-info/requires.txt
pyqpath.egg-info/top_level.txt
test/test_path_weights.py