Metadata-Version: 2.1
Name: pyqpath
Version: 0.0.1
Summary: PyQPath is a Python package to perform computations with path complexes.
Home-page: https://github.com/heitorbaldo/pyqpath
Author: Heitor Baldo
Author-email: heitorbaldo@gmail.com
Maintainer: PyQPath Developers
License: MIT License
Keywords: Path Complexes,Algebraic Topology,TDA
Platform: Linux
Platform: Mac OSX
Platform: Windows
Platform: Unix
Classifier: Development Status :: 2 - Pre-Alpha
Classifier: Intended Audience :: Developers
Classifier: Intended Audience :: Science/Research
Classifier: License :: OSI Approved :: MIT License
Classifier: Operating System :: OS Independent
Classifier: Programming Language :: Python :: 3
Classifier: Programming Language :: Python :: 3.7
Classifier: Programming Language :: Python :: 3.8
Classifier: Programming Language :: Python :: 3.9
Classifier: Programming Language :: Python :: 3 :: Only
Classifier: Topic :: Software Development :: Libraries :: Python Modules
Classifier: Topic :: Scientific/Engineering
License-File: LICENSE.txt
